alfabet/__init__.py
alfabet/_version.py
alfabet/drawing.py
alfabet/fragment.py
alfabet/model.py
alfabet/neighbors.py
alfabet/prediction.py
alfabet/preprocessor.py
alfabet-0.4.1.dist-info/LICENSE
alfabet-0.4.1.dist-info/METADATA
alfabet-0.4.1.dist-info/WHEEL
alfabet-0.4.1.dist-info/top_level.txt
alfabet-0.4.1.dist-info/RECORD
