Metadata-Version: 2.1
Name: alfabet
Version: 0.4.1
Summary: A library to estimate bond dissociation energies (BDEs) of organic molecules
Home-page: https://github.com/NREL/alfabet
Author: Peter St. John
Author-email: peter.stjohn@nrel.gov
Project-URL: Source, https://github.com/NREL/alfabet
Classifier: Development Status :: 3 - Alpha
Classifier: Intended Audience :: Developers
Classifier: License :: OSI Approved :: MIT License
Classifier: Programming Language :: Python :: 3
Classifier: Programming Language :: Python :: 3.4
Classifier: Programming Language :: Python :: 3.5
Classifier: Programming Language :: Python :: 3.6
Classifier: Programming Language :: Python :: 3.7
License-File: LICENSE
Requires-Dist: pandas
Requires-Dist: nfp (>=0.3.6)
Requires-Dist: tqdm
Requires-Dist: pooch
Requires-Dist: joblib
Requires-Dist: scikit-learn (==0.24.2)
